zip_code_radius-0.0.1.dist-info/RECORD
zip_code_radius-0.0.1.dist-info/top_level.txt
zip_code_radius-0.0.1.dist-info/WHEEL
zip_code_radius-0.0.1.dist-info/metadata.json
zip_code_radius-0.0.1.dist-info/METADATA
zip_code_radius-0.0.1.dist-info/DESCRIPTION.rst
zip_code_radius/distance.py
zip_code_radius/quadtree.py
zip_code_radius/solver.py
zip_code_radius/zip_code.py
zip_code_radius/settings.py
zip_code_radius/__init__.py
